starttls_policy_cli/__init__.py
starttls_policy_cli/configure.py
starttls_policy_cli/constants.py
starttls_policy_cli/main.py
starttls_policy_cli/policy.py
starttls_policy_cli/util.py
starttls_policy_cli/tests/__init__.py
starttls_policy_cli/tests/configure_test.py
starttls_policy_cli/tests/main_test.py
starttls_policy_cli/tests/policy_test.py
starttls_policy_cli/tests/util.py
starttls_policy_cli/tests/util_test.py
starttls_policy_cli-0.0.0.dev20190103.dist-info/DESCRIPTION.rst
starttls_policy_cli-0.0.0.dev20190103.dist-info/METADATA
starttls_policy_cli-0.0.0.dev20190103.dist-info/RECORD
starttls_policy_cli-0.0.0.dev20190103.dist-info/WHEEL
starttls_policy_cli-0.0.0.dev20190103.dist-info/entry_points.txt
starttls_policy_cli-0.0.0.dev20190103.dist-info/metadata.json
starttls_policy_cli-0.0.0.dev20190103.dist-info/top_level.txt
