Metadata-Version: 2.0
Name: starttls-policy-cli
Version: 0.0.0.dev20190103
Summary: Policy API for STARTTLS Preload
Home-page: https://github.com/EFForg/starttls-everywhere
Author: Sydney Li
Author-email: sydney@eff.org
License: Apache License 2.0
Platform: UNKNOWN
Classifier: Development Status :: 3 - Alpha
Classifier: Environment :: Plugins
Classifier: Intended Audience :: System Administrators
Classifier: License :: OSI Approved :: Apache Software License
Classifier: Operating System :: POSIX :: Linux
Classifier: Programming Language :: Python
Classifier: Programming Language :: Python :: 2
Classifier: Programming Language :: Python :: 2.7
Classifier: Programming Language :: Python :: 3
Classifier: Programming Language :: Python :: 3.3
Classifier: Topic :: Communications :: Email :: Mail Transport Agents
Classifier: Topic :: Security
Classifier: Topic :: System :: Installation/Setup
Classifier: Topic :: System :: Networking
Classifier: Topic :: System :: Systems Administration
Classifier: Topic :: Utilities
Provides-Extra: dev
Requires-Dist: datetime
Requires-Dist: python-dateutil
Requires-Dist: setuptools
Requires-Dist: six
Provides-Extra: dev
Requires-Dist: coverage; extra == 'dev'
Requires-Dist: mock; extra == 'dev'
Requires-Dist: pylint; extra == 'dev'
Requires-Dist: pytest; extra == 'dev'
Requires-Dist: pytest-cov; extra == 'dev'
Requires-Dist: setuptools (>=38.6.0); extra == 'dev'
Requires-Dist: wheel (>=0.31.0); extra == 'dev'
Requires-Dist: twine (>=1.11.0); extra == 'dev'
